{
  "best": {
    "name": "anchor_noop",
    "avg_log_loss": 0.5506436323122724,
    "Q1": 0.5912824734676818,
    "Q2": 0.6053216333386768,
    "Q3": 0.5887754061029061,
    "S1": 0.531237044773153,
    "S2": 0.5022154236865918,
    "S3": 0.4789955430003042,
    "S4": 0.5566779018165928,
    "encoder": NaN,
    "target_mode": NaN,
    "components": NaN,
    "alpha": NaN,
    "scale": NaN,
    "max_delta": NaN
  },
  "anchor_score": {
    "avg_log_loss": 0.5506436323122724,
    "Q1": 0.5912824734676818,
    "Q2": 0.6053216333386768,
    "Q3": 0.5887754061029061,
    "S1": 0.531237044773153,
    "S2": 0.5022154236865918,
    "S3": 0.4789955430003042,
    "S4": 0.5566779018165928
  },
  "feature_count": 1899,
  "folds": [
    {
      "fold": 1,
      "train_rows": 355,
      "valid_rows": 95,
      "kept_features": 1762
    },
    {
      "fold": 2,
      "train_rows": 358,
      "valid_rows": 92,
      "kept_features": 1764
    },
    {
      "fold": 3,
      "train_rows": 359,
      "valid_rows": 91,
      "kept_features": 1763
    },
    {
      "fold": 4,
      "train_rows": 363,
      "valid_rows": 87,
      "kept_features": 1764
    },
    {
      "fold": 5,
      "train_rows": 365,
      "valid_rows": 85,
      "kept_features": 1763
    }
  ],
  "args": {
    "train_path": "data/ch2026_metrics_train.csv",
    "sample_path": "data/ch2026_submission_sample.csv",
    "anchor_oof": "outputs/conditional_latent_routing_v25_joint_all_digest/oof_conditional_latent_routing.csv",
    "anchor_submission": "outputs/conditional_latent_routing_v25_joint_all_digest/submission_conditional_latent_routing.csv",
    "output_dir": "outputs/digest_label_aligned_encoder_v1_on_v25",
    "groups": "phone_recovery,social_rhythm,body_recovery,modality_desync",
    "folds": 5,
    "encoders": "pls,plspca",
    "target_modes": "logit_soft,prob",
    "components": "4,8,16",
    "alphas": "30,100,300",
    "scales": "0.025,0.05,0.075,0.1",
    "max_deltas": "0.1,0.2",
    "min_feature_std": 1e-06,
    "full_fit_top_k": 12,
    "seed": 2026
  }
}