{
  "base_avg_log_loss": 0.5818511527290617,
  "base_targets": {
    "Q1": 0.6358317172110295,
    "Q2": 0.6397670248932207,
    "Q3": 0.6213677582828048,
    "S1": 0.5542725406575977,
    "S2": 0.5292196070733155,
    "S3": 0.49841585304667624,
    "S4": 0.5940835679387884
  },
  "final_avg_log_loss": 0.5818511527290617,
  "final_targets": {
    "Q1": 0.6358317172110295,
    "Q2": 0.6397670248932207,
    "Q3": 0.6213677582828048,
    "S1": 0.5542725406575977,
    "S2": 0.5292196070733155,
    "S3": 0.49841585304667624,
    "S4": 0.5940835679387884
  },
  "feature_count": 245,
  "selection": [
    {
      "target": "Q1",
      "log_loss": 0.6355853338444569,
      "base_log_loss": 0.6358317172110295,
      "delta_vs_base": 0.00024638336657256676,
      "graph_name": "graph_bw3_sig1.5_sh0.25",
      "blend_weight": 0.05,
      "folds_improved": 2,
      "used": false
    },
    {
      "target": "Q2",
      "log_loss": 0.6400218597715194,
      "base_log_loss": 0.6397670248932207,
      "delta_vs_base": -0.0002548348782986931,
      "graph_name": "graph_bw2_sig7_sh0.25",
      "blend_weight": 0.025,
      "folds_improved": 3,
      "used": false
    },
    {
      "target": "Q3",
      "log_loss": 0.6215050174484305,
      "base_log_loss": 0.6213677582828048,
      "delta_vs_base": -0.00013725916562568052,
      "graph_name": "graph_bw1_sig2.5_sh0.25",
      "blend_weight": 0.025,
      "folds_improved": 3,
      "used": false
    },
    {
      "target": "S1",
      "log_loss": 0.5542514217424865,
      "base_log_loss": 0.5542725406575977,
      "delta_vs_base": 2.111891511114017e-05,
      "graph_name": "graph_bw2_sig1.5_sh0.25",
      "blend_weight": 0.025,
      "folds_improved": 3,
      "used": false
    },
    {
      "target": "S2",
      "log_loss": 0.5293869895230119,
      "base_log_loss": 0.5292196070733155,
      "delta_vs_base": -0.00016738244969638494,
      "graph_name": "graph_bw13_sig1.5_sh0.25",
      "blend_weight": 0.025,
      "folds_improved": 2,
      "used": false
    },
    {
      "target": "S3",
      "log_loss": 0.4983138891494765,
      "base_log_loss": 0.49841585304667624,
      "delta_vs_base": 0.00010196389719974164,
      "graph_name": "graph_bw1_sig4_sh0.25",
      "blend_weight": 0.025,
      "folds_improved": 3,
      "used": false
    },
    {
      "target": "S4",
      "log_loss": 0.5941040588571448,
      "base_log_loss": 0.5940835679387884,
      "delta_vs_base": -2.0490918356430576e-05,
      "graph_name": "graph_bw2_sig1.5_sh0.25",
      "blend_weight": 0.025,
      "folds_improved": 2,
      "used": false
    }
  ],
  "top_candidates": [
    {
      "name": "blend_w0.025_graph_bw2_sig7_sh0.25",
      "graph_name": "graph_bw2_sig7_sh0.25",
      "blend_weight": 0.025,
      "avg_log_loss": 0.5821696597338345,
      "Q1": 0.6358375147610308,
      "Q2": 0.6400218597715194,
      "Q3": 0.6215785787251803,
      "S1": 0.5550002613364383,
      "S2": 0.5294931755297596,
      "S3": 0.4986627961363339,
      "S4": 0.5945934318765799
    },
    {
      "name": "blend_w0.025_graph_bw1_sig4_sh0.25",
      "graph_name": "graph_bw1_sig4_sh0.25",
      "blend_weight": 0.025,
      "avg_log_loss": 0.5821716500659165,
      "Q1": 0.6358372529499632,
      "Q2": 0.6402699628501858,
      "Q3": 0.6215136999457536,
      "S1": 0.5550195049381462,
      "S2": 0.5295072499788326,
      "S3": 0.4983138891494765,
      "S4": 0.5947399906490586
    },
    {
      "name": "blend_w0.025_graph_bw2_sig1.5_sh0.25",
      "graph_name": "graph_bw2_sig1.5_sh0.25",
      "blend_weight": 0.025,
      "avg_log_loss": 0.5821838996320194,
      "Q1": 0.6357075812275635,
      "Q2": 0.640802367134254,
      "Q3": 0.6216890384469328,
      "S1": 0.5542514217424865,
      "S2": 0.5299123273263735,
      "S3": 0.4988205026893809,
      "S4": 0.5941040588571448
    },
    {
      "name": "blend_w0.025_graph_bw3_sig7_sh0.25",
      "graph_name": "graph_bw3_sig7_sh0.25",
      "blend_weight": 0.025,
      "avg_log_loss": 0.5821902857220042,
      "Q1": 0.6359410167710806,
      "Q2": 0.6400328963825284,
      "Q3": 0.6216374838411421,
      "S1": 0.5548564843685241,
      "S2": 0.5295228770265663,
      "S3": 0.49877248230606597,
      "S4": 0.5945687593581219
    },
    {
      "name": "blend_w0.025_graph_bw1_sig7_sh0.25",
      "graph_name": "graph_bw1_sig7_sh0.25",
      "blend_weight": 0.025,
      "avg_log_loss": 0.5821947761475812,
      "Q1": 0.6356874004227787,
      "Q2": 0.6402064968468124,
      "Q3": 0.6215818814396736,
      "S1": 0.5552503676863173,
      "S2": 0.5294858658113132,
      "S3": 0.49858772322789124,
      "S4": 0.5945636975982818
    },
    {
      "name": "blend_w0.025_graph_bw5_sig7_sh0.25",
      "graph_name": "graph_bw5_sig7_sh0.25",
      "blend_weight": 0.025,
      "avg_log_loss": 0.582244136287177,
      "Q1": 0.6361471333224068,
      "Q2": 0.6401608170668424,
      "Q3": 0.621807515779965,
      "S1": 0.55465682680989,
      "S2": 0.5295368975329007,
      "S3": 0.49885610532707747,
      "S4": 0.5945436581711568
    },
    {
      "name": "blend_w0.025_graph_bw1_sig4_sh0.5",
      "graph_name": "graph_bw1_sig4_sh0.5",
      "blend_weight": 0.025,
      "avg_log_loss": 0.5822718528669973,
      "Q1": 0.6359281865524226,
      "Q2": 0.640433919919422,
      "Q3": 0.6217053528831128,
      "S1": 0.5549099535656601,
      "S2": 0.5296325595970076,
      "S3": 0.4985425179211368,
      "S4": 0.5947504796302195
    },
    {
      "name": "blend_w0.025_graph_bw2_sig7_sh0.5",
      "graph_name": "graph_bw2_sig7_sh0.5",
      "blend_weight": 0.025,
      "avg_log_loss": 0.5822789621155365,
      "Q1": 0.6359388726268101,
      "Q2": 0.6402776935329506,
      "Q3": 0.6217577953178791,
      "S1": 0.5549021105750562,
      "S2": 0.5296301230716083,
      "S3": 0.49878574955410965,
      "S4": 0.5946603901303419
    },
    {
      "name": "blend_w0.025_graph_bw2_sig4_sh0.25",
      "graph_name": "graph_bw2_sig4_sh0.25",
      "blend_weight": 0.025,
      "avg_log_loss": 0.582279841349383,
      "Q1": 0.6360542321333368,
      "Q2": 0.6401532137276461,
      "Q3": 0.6216018903071807,
      "S1": 0.5548667508879475,
      "S2": 0.5296007889658134,
      "S3": 0.49876130987555417,
      "S4": 0.5949207035482026
    },
    {
      "name": "blend_w0.025_graph_bw1_sig7_sh0.5",
      "graph_name": "graph_bw1_sig7_sh0.5",
      "blend_weight": 0.025,
      "avg_log_loss": 0.5822890662338572,
      "Q1": 0.6358304164422783,
      "Q2": 0.640395247119746,
      "Q3": 0.621752569133826,
      "S1": 0.5550644127065746,
      "S2": 0.5296202569936298,
      "S3": 0.49872725426758097,
      "S4": 0.5946333069733656
    },
    {
      "name": "blend_w0.025_graph_bw2_sig1.5_sh0.5",
      "graph_name": "graph_bw2_sig1.5_sh0.5",
      "blend_weight": 0.025,
      "avg_log_loss": 0.5822935115319289,
      "Q1": 0.6358572504567489,
      "Q2": 0.6408053369940419,
      "Q3": 0.6218392257813579,
      "S1": 0.5544064803508001,
      "S2": 0.5299122365095061,
      "S3": 0.49889561035241536,
      "S4": 0.5943384402786318
    },
    {
      "name": "blend_w0.025_graph_bw3_sig7_sh0.5",
      "graph_name": "graph_bw3_sig7_sh0.5",
      "blend_weight": 0.025,
      "avg_log_loss": 0.5822957862020095,
      "Q1": 0.636011555461126,
      "Q2": 0.640288198850965,
      "Q3": 0.6218006463239775,
      "S1": 0.5548084904303444,
      "S2": 0.5296517762109213,
      "S3": 0.4988628019481847,
      "S4": 0.5946470341885478
    },
    {
      "name": "blend_w0.025_graph_bw8_sig7_sh0.25",
      "graph_name": "graph_bw8_sig7_sh0.25",
      "blend_weight": 0.025,
      "avg_log_loss": 0.5823224583353349,
      "Q1": 0.6363286807292141,
      "Q2": 0.6403568503346974,
      "Q3": 0.6219950945035546,
      "S1": 0.5545496107375815,
      "S2": 0.5295600281385763,
      "S3": 0.4988732434567564,
      "S4": 0.5945937004469649
    },
    {
      "name": "blend_w0.025_graph_bw3_sig4_sh0.25",
      "graph_name": "graph_bw3_sig4_sh0.25",
      "blend_weight": 0.025,
      "avg_log_loss": 0.5823281614162779,
      "Q1": 0.6361023481678743,
      "Q2": 0.6401595707270076,
      "Q3": 0.6216884467867906,
      "S1": 0.5547095026482469,
      "S2": 0.5297305537115347,
      "S3": 0.49892527988655855,
      "S4": 0.5949814279859327
    },
    {
      "name": "blend_w0.025_graph_bw5_sig7_sh0.5",
      "graph_name": "graph_bw5_sig7_sh0.5",
      "blend_weight": 0.025,
      "avg_log_loss": 0.5823344404588935,
      "Q1": 0.6361520911573949,
      "Q2": 0.6403768574431999,
      "Q3": 0.6219175400879511,
      "S1": 0.5546775078484505,
      "S2": 0.5296623622546609,
      "S3": 0.49892173666484346,
      "S4": 0.5946329877557535
    },
    {
      "name": "blend_w0.025_graph_bw3_sig1.5_sh0.25",
      "graph_name": "graph_bw3_sig1.5_sh0.25",
      "blend_weight": 0.025,
      "avg_log_loss": 0.58234434915343,
      "Q1": 0.6356588615034318,
      "Q2": 0.6410319326806347,
      "Q3": 0.6222203066107399,
      "S1": 0.5542636622102453,
      "S2": 0.5297082739531801,
      "S3": 0.49926288734231394,
      "S4": 0.5942645197734646
    },
    {
      "name": "blend_w0.025_graph_bw2_sig4_sh0.5",
      "graph_name": "graph_bw2_sig4_sh0.5",
      "blend_weight": 0.025,
      "avg_log_loss": 0.5823485774148718,
      "Q1": 0.6360780708002386,
      "Q2": 0.6403611257146703,
      "Q3": 0.6217691119660833,
      "S1": 0.5548104292001643,
      "S2": 0.5296983145189144,
      "S3": 0.498848275818024,
      "S4": 0.5948747138860072
    },
    {
      "name": "blend_w0.025_graph_bw3_sig4_sh0.5",
      "graph_name": "graph_bw3_sig4_sh0.5",
      "blend_weight": 0.025,
      "avg_log_loss": 0.5823831205070317,
      "Q1": 0.6361130374236392,
      "Q2": 0.6403683310494578,
      "Q3": 0.621829678577238,
      "S1": 0.5547068285933193,
      "S2": 0.5297859846385546,
      "S3": 0.498961117797143,
      "S4": 0.5949168654698697
    },
    {
      "name": "blend_w0.025_graph_bw8_sig7_sh0.5",
      "graph_name": "graph_bw8_sig7_sh0.5",
      "blend_weight": 0.025,
      "avg_log_loss": 0.582388461215034,
      "Q1": 0.6362749527913688,
      "Q2": 0.6405100179343723,
      "Q3": 0.6220449804393661,
      "S1": 0.5546074301492977,
      "S2": 0.5296787051788017,
      "S3": 0.49893493321217813,
      "S4": 0.5946682087998526
    },
    {
      "name": "blend_w0.025_graph_bw5_sig4_sh0.25",
      "graph_name": "graph_bw5_sig4_sh0.25",
      "blend_weight": 0.025,
      "avg_log_loss": 0.5823917859167359,
      "Q1": 0.6362788754618571,
      "Q2": 0.6402721518762371,
      "Q3": 0.6220050077045706,
      "S1": 0.5544559932199121,
      "S2": 0.5297257909929375,
      "S3": 0.4990412688649633,
      "S4": 0.5949634132966741
    }
  ],
  "args": {
    "master_path": "artifacts/10_master_daily.parquet",
    "latent_path": "outputs/diffusion_encoder/day_latents.parquet",
    "train_path": "data/ch2026_metrics_train.csv",
    "sample_path": "data/ch2026_submission_sample.csv",
    "base_oof": "outputs/block_aware_targetwise_transductive_q_count_vs_w03/oof_block_aware_targetwise_blend.csv",
    "base_submission": "outputs/block_aware_targetwise_transductive_q_count_vs_w03/submission_block_aware_targetwise_blend.csv",
    "output_dir": "outputs/graph_diffusion_on_block_qcount_min4",
    "folds": 5,
    "alpha": 10.0,
    "bandwidths": "1,2,3,5,8,13",
    "sigmas": "1.5,2.5,4,7",
    "label_shrinks": "0.25,0.5,0.75,0.9",
    "blend_weights": "0.025,0.05,0.1,0.15,0.2,0.3",
    "min_target_folds_improved": 4
  }
}